zipfile_deflate64/__init__.py
zipfile_deflate64/_patcher.py
zipfile_deflate64/_zipfile.py
zipfile_deflate64/deflate64.cpython-39-darwin.so
zipfile_deflate64_macos-0.1.0.dist-info/licenses/LICENSE
zipfile_deflate64_macos-0.1.0.dist-info/METADATA
zipfile_deflate64_macos-0.1.0.dist-info/WHEEL
zipfile_deflate64_macos-0.1.0.dist-info/top_level.txt
zipfile_deflate64_macos-0.1.0.dist-info/RECORD
